Methplotter/Methplotter.py
Methplotter/__init__.py
methplotter-1.5.dist-info/licenses/LICENSE
methplotter-1.5.dist-info/METADATA
methplotter-1.5.dist-info/WHEEL
methplotter-1.5.dist-info/top_level.txt
methplotter-1.5.dist-info/RECORD
